{
  "project_info": {
    "project_number": "217859276503",
    "firebase_url": "https://help-the-falling-people-231020.firebaseio.com",
    "project_id": "help-the-falling-people-231020",
    "storage_bucket": "help-the-falling-people-231020.appspot.com"
  },
  "client": [
    {
      "client_info": {
        "mobilesdk_app_id": "1:217859276503:android:0bd79b1d481209b8",
        "android_client_info": {
          "package_name": "com.diti.helpthefallingpeople"
        }
      },
      "oauth_client": [
        {
          "client_id": "217859276503-25koej12ukaoi4o73ddhp9mh7lcg717n.apps.googleusercontent.com",
          "client_type": 3
        }
      ],
      "api_key": [
        {
          "current_key": "AIzaSyAUCHEoZRrfqMf5P9fdrxKRlZeUBA5_acw"
        }
      ],
      "services": {
        "analytics_service": {
          "status": 1
        },
        "appinvite_service": {
          "status": 2,
          "other_platform_oauth_client": [
            {
              "client_id": "217859276503-25koej12ukaoi4o73ddhp9mh7lcg717n.apps.googleusercontent.com",
              "client_type": 3
            }
          ]
        },
        "ads_service": {
          "status": 2
        }
      }
    }
  ],
  "configuration_version": "1"
}